{
 "1525570650529832961": {
  "Sun Feb 19 20:05:15 +0000 2023": {
   "hashtags": [],
   "symbols": [],
   "user_mentions": [
    {
     "screen_name": "elonmusk",
     "name": "Elon Musk",
     "id": 44196397,
     "id_str": "44196397",
     "indices": [
      3,
      12
     ]
    }
   ],
   "urls": []
  },
  "Sun Feb 19 20:04:48 +0000 2023": {
   "hashtags": [],
   "symbols": [],
   "user_mentions": [
    {
     "screen_name": "Pastor__West",
     "name": "Pastor West",
     "id": 403443988,
     "id_str": "403443988",
     "indices": [
      3,
      16
     ]
    }
   ],
   "urls": []
  },
  "Sun Feb 19 20:03:56 +0000 2023": {
   "hashtags": [],
   "symbols": [],
   "user_mentions": [
    {
     "screen_name": "MKBHD",
     "name": "Marques Brownlee",
     "id": 29873662,
     "id_str": "29873662",
     "indices": [
      3,
      9
     ]
    }
   ],
   "urls": [],
   "media": [
    {
     "id": 1626069685308465152,
     "id_str": "1626069685308465152",
     "indices": [
      41,
      64
     ],
     "media_url": "http://pbs.twimg.com/media/FpD1w3TXoAAWb77.jpg",
     "media_url_https": "https://pbs.twimg.com/media/FpD1w3TXoAAWb77.jpg",
     "url": "https://t.co/52gBWvpenI",
     "display_url": "pic.twitter.com/52gBWvpenI",
     "expanded_url": "https://twitter.com/MKBHD/status/1626069687837634562/photo/1",
     "type": "photo",
     "sizes": {
      "small": {
       "w": 680,
       "h": 604,
       "resize": "fit"
      },
      "thumb": {
       "w": 150,
       "h": 150,
       "resize": "crop"
      },
      "medium": {
       "w": 1200,
       "h": 1066,
       "resize": "fit"
      },
      "large": {
       "w": 2048,
       "h": 1819,
       "resize": "fit"
      }
     },
     "source_status_id": 1626069687837634562,
     "source_status_id_str": "1626069687837634562",
     "source_user_id": 29873662,
     "source_user_id_str": "29873662"
    }
   ]
  },
  "Sun Feb 19 20:03:44 +0000 2023": {
   "hashtags": [],
   "symbols": [],
   "user_mentions": [
    {
     "screen_name": "elonmusk",
     "name": "Elon Musk",
     "id": 44196397,
     "id_str": "44196397",
     "indices": [
      3,
      12
     ]
    }
   ],
   "urls": []
  },
  "Sun Feb 19 20:02:17 +0000 2023": {
   "hashtags": [],
   "symbols": [],
   "user_mentions": [
    {
     "screen_name": "Naija_PR",
     "name": "Naija",
     "id": 1901298962,
     "id_str": "1901298962",
     "indices": [
      3,
      12
     ]
    }
   ],
   "urls": [],
   "media": [
    {
     "id": 1626918883880845312,
     "id_str": "1626918883880845312",
     "indices": [
      33,
      56
     ],
     "media_url": "http://pbs.twimg.com/media/FpP6GugXwAAQkyP.jpg",
     "media_url_https": "https://pbs.twimg.com/media/FpP6GugXwAAQkyP.jpg",
     "url": "https://t.co/U69vfFDVhS",
     "display_url": "pic.twitter.com/U69vfFDVhS",
     "expanded_url": "https://twitter.com/Naija_PR/status/1626918897151623170/photo/1",
     "type": "photo",
     "sizes": {
      "thumb": {
       "w": 150,
       "h": 150,
       "resize": "crop"
      },
      "large": {
       "w": 2048,
       "h": 2048,
       "resize": "fit"
      },
      "medium": {
       "w": 1200,
       "h": 1200,
       "resize": "fit"
      },
      "small": {
       "w": 680,
       "h": 680,
       "resize": "fit"
      }
     },
     "source_status_id": 1626918897151623170,
     "source_status_id_str": "1626918897151623170",
     "source_user_id": 1901298962,
     "source_user_id_str": "1901298962"
    }
   ]
  },
  "Sun Feb 19 20:01:58 +0000 2023": {
   "hashtags": [],
   "symbols": [],
   "user_mentions": [
    {
     "screen_name": "MKBHD",
     "name": "Marques Brownlee",
     "id": 29873662,
     "id_str": "29873662",
     "indices": [
      3,
      9
     ]
    }
   ],
   "urls": [
    {
     "url": "https://t.co/FdilmGJslB",
     "expanded_url": "https://youtu.be/7emz4zZ226E",
     "display_url": "youtu.be/7emz4zZ226E",
     "indices": [
      48,
      71
     ]
    }
   ],
   "media": [
    {
     "id": 1626744820549951490,
     "id_str": "1626744820549951490",
     "indices": [
      72,
      95
     ],
     "media_url": "http://pbs.twimg.com/media/FpNby6EWIAIAStN.jpg",
     "media_url_https": "https://pbs.twimg.com/media/FpNby6EWIAIAStN.jpg",
     "url": "https://t.co/VdnoNHFOsY",
     "display_url": "pic.twitter.com/VdnoNHFOsY",
     "expanded_url": "https://twitter.com/MKBHD/status/1626750803703697408/photo/1",
     "type": "photo",
     "sizes": {
      "thumb": {
       "w": 150,
       "h": 150,
       "resize": "crop"
      },
      "small": {
       "w": 680,
       "h": 383,
       "resize": "fit"
      },
      "medium": {
       "w": 1200,
       "h": 675,
       "resize": "fit"
      },
      "large": {
       "w": 1920,
       "h": 1080,
       "resize": "fit"
      }
     },
     "source_status_id": 1626750803703697408,
     "source_status_id_str": "1626750803703697408",
     "source_user_id": 29873662,
     "source_user_id_str": "29873662"
    }
   ]
  },
  "Sun Feb 19 20:01:52 +0000 2023": {
   "hashtags": [],
   "symbols": [],
   "user_mentions": [
    {
     "screen_name": "elonmusk",
     "name": "Elon Musk",
     "id": 44196397,
     "id_str": "44196397",
     "indices": [
      3,
      12
     ]
    }
   ],
   "urls": [],
   "media": [
    {
     "id": 1627377245751857152,
     "id_str": "1627377245751857152",
     "indices": [
      71,
      94
     ],
     "media_url": "http://pbs.twimg.com/media/FpWa-5iX0AAU-8d.jpg",
     "media_url_https": "https://pbs.twimg.com/media/FpWa-5iX0AAU-8d.jpg",
     "url": "https://t.co/B1JQFC7Ojh",
     "display_url": "pic.twitter.com/B1JQFC7Ojh",
     "expanded_url": "https://twitter.com/elonmusk/status/1627377252777226242/photo/1",
     "type": "photo",
     "sizes": {
      "thumb": {
       "w": 150,
       "h": 150,
       "resize": "crop"
      },
      "small": {
       "w": 680,
       "h": 383,
       "resize": "fit"
      },
      "large": {
       "w": 983,
       "h": 554,
       "resize": "fit"
      },
      "medium": {
       "w": 983,
       "h": 554,
       "resize": "fit"
      }
     },
     "source_status_id": 1627377252777226242,
     "source_status_id_str": "1627377252777226242",
     "source_user_id": 44196397,
     "source_user_id_str": "44196397"
    }
   ]
  },
  "Sun Feb 19 20:01:23 +0000 2023": {
   "hashtags": [],
   "symbols": [],
   "user_mentions": [
    {
     "screen_name": "elonmusk",
     "name": "Elon Musk",
     "id": 44196397,
     "id_str": "44196397",
     "indices": [
      3,
      12
     ]
    }
   ],
   "urls": [],
   "media": [
    {
     "id": 1627381661997342721,
     "id_str": "1627381661997342721",
     "indices": [
      14,
      37
     ],
     "media_url": "http://pbs.twimg.com/media/FpWe_9VWIAEPAaM.jpg",
     "media_url_https": "https://pbs.twimg.com/media/FpWe_9VWIAEPAaM.jpg",
     "url": "https://t.co/Az4RSAMvoE",
     "display_url": "pic.twitter.com/Az4RSAMvoE",
     "expanded_url": "https://twitter.com/elonmusk/status/1627381669601636358/photo/1",
     "type": "photo",
     "sizes": {
      "thumb": {
       "w": 150,
       "h": 150,
       "resize": "crop"
      },
      "small": {
       "w": 680,
       "h": 521,
       "resize": "fit"
      },
      "medium": {
       "w": 951,
       "h": 729,
       "resize": "fit"
      },
      "large": {
       "w": 951,
       "h": 729,
       "resize": "fit"
      }
     },
     "source_status_id": 1627381669601636358,
     "source_status_id_str": "1627381669601636358",
     "source_user_id": 44196397,
     "source_user_id_str": "44196397"
    }
   ]
  },
  "Sun Feb 19 20:01:17 +0000 2023": {
   "hashtags": [],
   "symbols": [],
   "user_mentions": [
    {
     "screen_name": "elonmusk",
     "name": "Elon Musk",
     "id": 44196397,
     "id_str": "44196397",
     "indices": [
      3,
      12
     ]
    }
   ],
   "urls": [],
   "media": [
    {
     "id": 1627380447431823363,
     "id_str": "1627380447431823363",
     "indices": [
      14,
      37
     ],
     "media_url": "http://pbs.twimg.com/media/FpWd5QuXEAMT3xP.jpg",
     "media_url_https": "https://pbs.twimg.com/media/FpWd5QuXEAMT3xP.jpg",
     "url": "https://t.co/qzDTuGsZY1",
     "display_url": "pic.twitter.com/qzDTuGsZY1",
     "expanded_url": "https://twitter.com/elonmusk/status/1627380454067142658/photo/1",
     "type": "photo",
     "sizes": {
      "thumb": {
       "w": 150,
       "h": 150,
       "resize": "crop"
      },
      "small": {
       "w": 480,
       "h": 680,
       "resize": "fit"
      },
      "large": {
       "w": 499,
       "h": 707,
       "resize": "fit"
      },
      "medium": {
       "w": 499,
       "h": 707,
       "resize": "fit"
      }
     },
     "source_status_id": 1627380454067142658,
     "source_status_id_str": "1627380454067142658",
     "source_user_id": 44196397,
     "source_user_id_str": "44196397"
    }
   ]
  },
  "Sun Feb 19 20:00:57 +0000 2023": {
   "hashtags": [],
   "symbols": [],
   "user_mentions": [
    {
     "screen_name": "PulseNigeria247",
     "name": "Pulse Nigeria",
     "id": 374999591,
     "id_str": "374999591",
     "indices": [
      3,
      19
     ]
    }
   ],
   "urls": [],
   "media": [
    {
     "id": 1626901237248434179,
     "id_str": "1626901237248434179",
     "indices": [
      66,
      89
     ],
     "media_url": "http://pbs.twimg.com/media/FpPqDjrWIAM5Yb9.jpg",
     "media_url_https": "https://pbs.twimg.com/media/FpPqDjrWIAM5Yb9.jpg",
     "url": "https://t.co/UQJlJNsmPM",
     "display_url": "pic.twitter.com/UQJlJNsmPM",
     "expanded_url": "https://twitter.com/PulseNigeria247/status/1626901243250544644/photo/1",
     "type": "photo",
     "sizes": {
      "thumb": {
       "w": 150,
       "h": 150,
       "resize": "crop"
      },
      "small": {
       "w": 680,
       "h": 575,
       "resize": "fit"
      },
      "medium": {
       "w": 687,
       "h": 581,
       "resize": "fit"
      },
      "large": {
       "w": 687,
       "h": 581,
       "resize": "fit"
      }
     },
     "source_status_id": 1626901243250544644,
     "source_status_id_str": "1626901243250544644",
     "source_user_id": 374999591,
     "source_user_id_str": "374999591"
    }
   ]
  },
  "Sun Feb 19 20:00:44 +0000 2023": {
   "hashtags": [],
   "symbols": [],
   "user_mentions": [
    {
     "screen_name": "instablog9ja",
     "name": "Instablog9ja",
     "id": 754393222563102720,
     "id_str": "754393222563102720",
     "indices": [
      3,
      16
     ]
    }
   ],
   "urls": []
  },
  "Sun Feb 19 19:59:52 +0000 2023": {
   "hashtags": [],
   "symbols": [],
   "user_mentions": [
    {
     "screen_name": "Naija_PR",
     "name": "Naija",
     "id": 1901298962,
     "id_str": "1901298962",
     "indices": [
      3,
      12
     ]
    }
   ],
   "urls": [],
   "media": [
    {
     "id": 1627322913060683776,
     "id_str": "1627322913060683776",
     "indices": [
      24,
      47
     ],
     "media_url": "http://pbs.twimg.com/media/FpVpkUfWAAABqz2.jpg",
     "media_url_https": "https://pbs.twimg.com/media/FpVpkUfWAAABqz2.jpg",
     "url": "https://t.co/oD4d2T4t9z",
     "display_url": "pic.twitter.com/oD4d2T4t9z",
     "expanded_url": "https://twitter.com/Naija_PR/status/1627322922485309442/photo/1",
     "type": "photo",
     "sizes": {
      "thumb": {
       "w": 150,
       "h": 150,
       "resize": "crop"
      },
      "large": {
       "w": 2048,
       "h": 2048,
       "resize": "fit"
      },
      "small": {
       "w": 680,
       "h": 680,
       "resize": "fit"
      },
      "medium": {
       "w": 1200,
       "h": 1200,
       "resize": "fit"
      }
     },
     "source_status_id": 1627322922485309442,
     "source_status_id_str": "1627322922485309442",
     "source_user_id": 1901298962,
     "source_user_id_str": "1901298962"
    }
   ]
  },
  "Sun Feb 19 19:59:34 +0000 2023": {
   "hashtags": [],
   "symbols": [],
   "user_mentions": [
    {
     "screen_name": "instablog9ja",
     "name": "Instablog9ja",
     "id": 754393222563102720,
     "id_str": "754393222563102720",
     "indices": [
      3,
      16
     ]
    }
   ],
   "urls": []
  },
  "Fri Feb 17 18:45:27 +0000 2023": {
   "hashtags": [],
   "symbols": [],
   "user_mentions": [
    {
     "screen_name": "instablog9ja",
     "name": "Instablog9ja",
     "id": 754393222563102720,
     "id_str": "754393222563102720",
     "indices": [
      3,
      16
     ]
    }
   ],
   "urls": [],
   "media": [
    {
     "id": 1626581117221601282,
     "id_str": "1626581117221601282",
     "indices": [
      82,
      105
     ],
     "media_url": "http://pbs.twimg.com/media/FpLG6HpaAAIg1L3.jpg",
     "media_url_https": "https://pbs.twimg.com/media/FpLG6HpaAAIg1L3.jpg",
     "url": "https://t.co/n4hHr18TVW",
     "display_url": "pic.twitter.com/n4hHr18TVW",
     "expanded_url": "https://twitter.com/instablog9ja/status/1626581130714677253/photo/1",
     "type": "photo",
     "sizes": {
      "thumb": {
       "w": 150,
       "h": 150,
       "resize": "crop"
      },
      "medium": {
       "w": 748,
       "h": 920,
       "resize": "fit"
      },
      "small": {
       "w": 553,
       "h": 680,
       "resize": "fit"
      },
      "large": {
       "w": 748,
       "h": 920,
       "resize": "fit"
      }
     },
     "source_status_id": 1626581130714677253,
     "source_status_id_str": "1626581130714677253",
     "source_user_id": 754393222563102720,
     "source_user_id_str": "754393222563102720"
    }
   ]
  },
  "Fri Feb 17 18:44:27 +0000 2023": {
   "hashtags": [],
   "symbols": [],
   "user_mentions": [
    {
     "screen_name": "instablog9ja",
     "name": "Instablog9ja",
     "id": 754393222563102720,
     "id_str": "754393222563102720",
     "indices": [
      3,
      16
     ]
    }
   ],
   "urls": []
  },
  "Fri Feb 17 18:35:07 +0000 2023": {
   "hashtags": [],
   "symbols": [],
   "user_mentions": [
    {
     "screen_name": "bod_republic",
     "name": "B.O.D",
     "id": 3138923027,
     "id_str": "3138923027",
     "indices": [
      3,
      16
     ]
    }
   ],
   "urls": []
  },
  "Fri Feb 17 18:34:39 +0000 2023": {
   "hashtags": [],
   "symbols": [],
   "user_mentions": [
    {
     "screen_name": "elonmusk",
     "name": "Elon Musk",
     "id": 44196397,
     "id_str": "44196397",
     "indices": [
      3,
      12
     ]
    },
    {
     "screen_name": "TheRabbitHole84",
     "name": "The Rabbit Hole",
     "id": 1485689970593468416,
     "id_str": "1485689970593468416",
     "indices": [
      14,
      30
     ]
    }
   ],
   "urls": [],
   "media": [
    {
     "id": 1626295790254845952,
     "id_str": "1626295790254845952",
     "indices": [
      78,
      101
     ],
     "media_url": "http://pbs.twimg.com/media/FpHDZ53acAA8miE.jpg",
     "media_url_https": "https://pbs.twimg.com/media/FpHDZ53acAA8miE.jpg",
     "url": "https://t.co/nGHLDB5Ycx",
     "display_url": "pic.twitter.com/nGHLDB5Ycx",
     "expanded_url": "https://twitter.com/elonmusk/status/1626295793853534209/photo/1",
     "type": "photo",
     "sizes": {
      "large": {
       "w": 339,
       "h": 149,
       "resize": "fit"
      },
      "medium": {
       "w": 339,
       "h": 149,
       "resize": "fit"
      },
      "small": {
       "w": 339,
       "h": 149,
       "resize": "fit"
      },
      "thumb": {
       "w": 149,
       "h": 149,
       "resize": "crop"
      }
     },
     "source_status_id": 1626295793853534209,
     "source_status_id_str": "1626295793853534209",
     "source_user_id": 44196397,
     "source_user_id_str": "44196397"
    }
   ]
  },
  "Fri Feb 17 07:21:25 +0000 2023": {
   "hashtags": [],
   "symbols": [],
   "user_mentions": [
    {
     "screen_name": "MattWallace888",
     "name": "Matt Wallace",
     "id": 805532293951606785,
     "id_str": "805532293951606785",
     "indices": [
      3,
      18
     ]
    }
   ],
   "urls": []
  },
  "Fri Feb 17 07:21:09 +0000 2023": {
   "hashtags": [],
   "symbols": [],
   "user_mentions": [
    {
     "screen_name": "instablog9ja",
     "name": "Instablog9ja",
     "id": 754393222563102720,
     "id_str": "754393222563102720",
     "indices": [
      0,
      13
     ]
    }
   ],
   "urls": []
  },
  "Fri Feb 17 07:05:24 +0000 2023": {
   "hashtags": [],
   "symbols": [],
   "user_mentions": [
    {
     "screen_name": "elonmusk",
     "name": "Elon Musk",
     "id": 44196397,
     "id_str": "44196397",
     "indices": [
      3,
      12
     ]
    }
   ],
   "urls": []
  },
  "Fri Feb 17 07:01:08 +0000 2023": {
   "hashtags": [],
   "symbols": [],
   "user_mentions": [
    {
     "screen_name": "elonmusk",
     "name": "Elon Musk",
     "id": 44196397,
     "id_str": "44196397",
     "indices": [
      3,
      12
     ]
    },
    {
     "screen_name": "ray4tesla",
     "name": "Ray",
     "id": 959168599519764480,
     "id_str": "959168599519764480",
     "indices": [
      14,
      24
     ]
    }
   ],
   "urls": []
  },
  "Fri Feb 17 07:00:52 +0000 2023": {
   "hashtags": [],
   "symbols": [],
   "user_mentions": [
    {
     "screen_name": "ray4tesla",
     "name": "Ray",
     "id": 959168599519764480,
     "id_str": "959168599519764480",
     "indices": [
      3,
      13
     ]
    },
    {
     "screen_name": "elonmusk",
     "name": "Elon Musk",
     "id": 44196397,
     "id_str": "44196397",
     "indices": [
      72,
      81
     ]
    }
   ],
   "urls": []
  },
  "Fri Feb 17 07:00:25 +0000 2023": {
   "hashtags": [
    {
     "text": "CRYPTOLOVER",
     "indices": [
      41,
      53
     ]
    }
   ],
   "symbols": [],
   "user_mentions": [
    {
     "screen_name": "JaytunezBeatz",
     "name": "Big Jay \ud83e\udd85\ud83d\udc9c\u2764\ufe0f\ud83d\udcaf",
     "id": 961545605704282112,
     "id_str": "961545605704282112",
     "indices": [
      3,
      17
     ]
    },
    {
     "screen_name": "binance",
     "name": "Binance",
     "id": 877807935493033984,
     "id_str": "877807935493033984",
     "indices": [
      19,
      27
     ]
    }
   ],
   "urls": [],
   "media": [
    {
     "id": 1623220863569985537,
     "id_str": "1623220863569985537",
     "indices": [
      54,
      77
     ],
     "media_url": "http://pbs.twimg.com/media/FobWxnUXgAENBVO.jpg",
     "media_url_https": "https://pbs.twimg.com/media/FobWxnUXgAENBVO.jpg",
     "url": "https://t.co/KSKYqFRsDF",
     "display_url": "pic.twitter.com/KSKYqFRsDF",
     "expanded_url": "https://twitter.com/JaytunezBeatz/status/1623220881349656576/photo/1",
     "type": "photo",
     "sizes": {
      "thumb": {
       "w": 150,
       "h": 150,
       "resize": "crop"
      },
      "medium": {
       "w": 853,
       "h": 1200,
       "resize": "fit"
      },
      "large": {
       "w": 981,
       "h": 1380,
       "resize": "fit"
      },
      "small": {
       "w": 483,
       "h": 680,
       "resize": "fit"
      }
     },
     "source_status_id": 1623220881349656576,
     "source_status_id_str": "1623220881349656576",
     "source_user_id": 961545605704282112,
     "source_user_id_str": "961545605704282112"
    }
   ]
  },
  "Fri Feb 17 07:00:07 +0000 2023": {
   "hashtags": [],
   "symbols": [],
   "user_mentions": [
    {
     "screen_name": "marylizbender",
     "name": "MaryLiz Bender",
     "id": 978656433662283776,
     "id_str": "978656433662283776",
     "indices": [
      3,
      17
     ]
    },
    {
     "screen_name": "elonmusk",
     "name": "Elon Musk",
     "id": 44196397,
     "id_str": "44196397",
     "indices": [
      19,
      28
     ]
    },
    {
     "screen_name": "considercosmos",
     "name": "Cosmic Perspective",
     "id": 1050516235178237952,
     "id_str": "1050516235178237952",
     "indices": [
      29,
      44
     ]
    },
    {
     "screen_name": "SpaceX",
     "name": "SpaceX",
     "id": 34743251,
     "id_str": "34743251",
     "indices": [
      45,
      52
     ]
    }
   ],
   "urls": []
  },
  "Fri Feb 17 06:59:52 +0000 2023": {
   "hashtags": [],
   "symbols": [],
   "user_mentions": [
    {
     "screen_name": "BaileeParis",
     "name": "Bailee Paris",
     "id": 976637245917749248,
     "id_str": "976637245917749248",
     "indices": [
      3,
      15
     ]
    },
    {
     "screen_name": "MattWallace888",
     "name": "Matt Wallace",
     "id": 805532293951606785,
     "id_str": "805532293951606785",
     "indices": [
      17,
      32
     ]
    },
    {
     "screen_name": "elonmusk",
     "name": "Elon Musk",
     "id": 44196397,
     "id_str": "44196397",
     "indices": [
      33,
      42
     ]
    },
    {
     "screen_name": "considercosmos",
     "name": "Cosmic Perspective",
     "id": 1050516235178237952,
     "id_str": "1050516235178237952",
     "indices": [
      43,
      58
     ]
    },
    {
     "screen_name": "SpaceX",
     "name": "SpaceX",
     "id": 34743251,
     "id_str": "34743251",
     "indices": [
      59,
      66
     ]
    }
   ],
   "urls": []
  },
  "Fri Feb 17 06:59:48 +0000 2023": {
   "hashtags": [],
   "symbols": [],
   "user_mentions": [
    {
     "screen_name": "BaileeParis",
     "name": "Bailee Paris",
     "id": 976637245917749248,
     "id_str": "976637245917749248",
     "indices": [
      3,
      15
     ]
    }
   ],
   "urls": []
  },
  "Fri Feb 17 06:58:17 +0000 2023": {
   "hashtags": [],
   "symbols": [],
   "user_mentions": [
    {
     "screen_name": "bod_republic",
     "name": "B.O.D",
     "id": 3138923027,
     "id_str": "3138923027",
     "indices": [
      3,
      16
     ]
    }
   ],
   "urls": []
  },
  "Fri Feb 17 06:58:06 +0000 2023": {
   "hashtags": [],
   "symbols": [],
   "user_mentions": [
    {
     "screen_name": "elonmusk",
     "name": "Elon Musk",
     "id": 44196397,
     "id_str": "44196397",
     "indices": [
      3,
      12
     ]
    },
    {
     "screen_name": "considercosmos",
     "name": "Cosmic Perspective",
     "id": 1050516235178237952,
     "id_str": "1050516235178237952",
     "indices": [
      14,
      29
     ]
    },
    {
     "screen_name": "SpaceX",
     "name": "SpaceX",
     "id": 34743251,
     "id_str": "34743251",
     "indices": [
      30,
      37
     ]
    }
   ],
   "urls": []
  },
  "Fri Feb 17 06:58:03 +0000 2023": {
   "hashtags": [],
   "symbols": [],
   "user_mentions": [
    {
     "screen_name": "considercosmos",
     "name": "Cosmic Perspective",
     "id": 1050516235178237952,
     "id_str": "1050516235178237952",
     "indices": [
      3,
      18
     ]
    }
   ],
   "urls": []
  },
  "Fri Feb 17 06:56:37 +0000 2023": {
   "hashtags": [],
   "symbols": [],
   "user_mentions": [
    {
     "screen_name": "NBA_Africa",
     "name": "NBA Africa",
     "id": 789429338,
     "id_str": "789429338",
     "indices": [
      3,
      14
     ]
    },
    {
     "screen_name": "ESPNAfrica",
     "name": "ESPN Africa",
     "id": 4226383180,
     "id_str": "4226383180",
     "indices": [
      122,
      133
     ]
    }
   ],
   "urls": []
  },
  "Fri Feb 17 06:56:11 +0000 2023": {
   "hashtags": [
    {
     "text": "CRYPTOLOVER",
     "indices": [
      32,
      44
     ]
    }
   ],
   "symbols": [],
   "user_mentions": [
    {
     "screen_name": "JaytunezBeatz",
     "name": "Big Jay \ud83e\udd85\ud83d\udc9c\u2764\ufe0f\ud83d\udcaf",
     "id": 961545605704282112,
     "id_str": "961545605704282112",
     "indices": [
      3,
      17
     ]
    },
    {
     "screen_name": "binance",
     "name": "Binance",
     "id": 877807935493033984,
     "id_str": "877807935493033984",
     "indices": [
      46,
      54
     ]
    }
   ],
   "urls": [],
   "media": [
    {
     "id": 1623220418961195009,
     "id_str": "1623220418961195009",
     "indices": [
      56,
      79
     ],
     "media_url": "http://pbs.twimg.com/media/FobWXvBXwAE01rD.jpg",
     "media_url_https": "https://pbs.twimg.com/media/FobWXvBXwAE01rD.jpg",
     "url": "https://t.co/Er35U5zuyR",
     "display_url": "pic.twitter.com/Er35U5zuyR",
     "expanded_url": "https://twitter.com/JaytunezBeatz/status/1623220429644083200/photo/1",
     "type": "photo",
     "sizes": {
      "thumb": {
       "w": 150,
       "h": 150,
       "resize": "crop"
      },
      "medium": {
       "w": 853,
       "h": 1200,
       "resize": "fit"
      },
      "large": {
       "w": 981,
       "h": 1380,
       "resize": "fit"
      },
      "small": {
       "w": 483,
       "h": 680,
       "resize": "fit"
      }
     },
     "source_status_id": 1623220429644083200,
     "source_status_id_str": "1623220429644083200",
     "source_user_id": 961545605704282112,
     "source_user_id_str": "961545605704282112"
    }
   ]
  },
  "Fri Feb 17 06:55:28 +0000 2023": {
   "hashtags": [],
   "symbols": [],
   "user_mentions": [
    {
     "screen_name": "elonmusk",
     "name": "Elon Musk",
     "id": 44196397,
     "id_str": "44196397",
     "indices": [
      3,
      12
     ]
    }
   ],
   "urls": [],
   "media": [
    {
     "id": 1623182543620132869,
     "id_str": "1623182543620132869",
     "indices": [
      16,
      39
     ],
     "media_url": "http://pbs.twimg.com/media/Foaz7GYX0AU9unl.jpg",
     "media_url_https": "https://pbs.twimg.com/media/Foaz7GYX0AU9unl.jpg",
     "url": "https://t.co/jL5fjQxTcz",
     "display_url": "pic.twitter.com/jL5fjQxTcz",
     "expanded_url": "https://twitter.com/elonmusk/status/1623182547373985793/photo/1",
     "type": "photo",
     "sizes": {
      "thumb": {
       "w": 150,
       "h": 150,
       "resize": "crop"
      },
      "large": {
       "w": 800,
       "h": 673,
       "resize": "fit"
      },
      "medium": {
       "w": 800,
       "h": 673,
       "resize": "fit"
      },
      "small": {
       "w": 680,
       "h": 572,
       "resize": "fit"
      }
     },
     "source_status_id": 1623182547373985793,
     "source_status_id_str": "1623182547373985793",
     "source_user_id": 44196397,
     "source_user_id_str": "44196397"
    }
   ]
  },
  "Fri Feb 17 06:55:09 +0000 2023": {
   "hashtags": [
    {
     "text": "MyTwitterAnniversary",
     "indices": [
      66,
      87
     ]
    }
   ],
   "symbols": [],
   "user_mentions": [
    {
     "screen_name": "JaytunezBeatz",
     "name": "Big Jay \ud83e\udd85\ud83d\udc9c\u2764\ufe0f\ud83d\udcaf",
     "id": 961545605704282112,
     "id_str": "961545605704282112",
     "indices": [
      3,
      17
     ]
    }
   ],
   "urls": [],
   "media": [
    {
     "id": 1623218887998201856,
     "id_str": "1623218887998201856",
     "indices": [
      88,
      111
     ],
     "media_url": "http://pbs.twimg.com/media/FobU-nvWYAAF9oM.jpg",
     "media_url_https": "https://pbs.twimg.com/media/FobU-nvWYAAF9oM.jpg",
     "url": "https://t.co/cWj0jwAbFS",
     "display_url": "pic.twitter.com/cWj0jwAbFS",
     "expanded_url": "https://twitter.com/JaytunezBeatz/status/1623218898353938433/photo/1",
     "type": "photo",
     "sizes": {
      "thumb": {
       "w": 150,
       "h": 150,
       "resize": "crop"
      },
      "small": {
       "w": 680,
       "h": 383,
       "resize": "fit"
      },
      "medium": {
       "w": 1200,
       "h": 675,
       "resize": "fit"
      },
      "large": {
       "w": 1920,
       "h": 1080,
       "resize": "fit"
      }
     },
     "source_status_id": 1623218898353938433,
     "source_status_id_str": "1623218898353938433",
     "source_user_id": 961545605704282112,
     "source_user_id_str": "961545605704282112"
    }
   ]
  },
  "Fri Feb 17 06:54:50 +0000 2023": {
   "hashtags": [],
   "symbols": [],
   "user_mentions": [
    {
     "screen_name": "Wisdom_HQ",
     "name": "Wisdom",
     "id": 1355814872408317958,
     "id_str": "1355814872408317958",
     "indices": [
      3,
      13
     ]
    }
   ],
   "urls": [],
   "media": [
    {
     "id": 1620323771537330177,
     "id_str": "1620323771537330177",
     "indices": [
      15,
      38
     ],
     "media_url": "http://pbs.twimg.com/media/FnyL4qeakAE_QOP.jpg",
     "media_url_https": "https://pbs.twimg.com/media/FnyL4qeakAE_QOP.jpg",
     "url": "https://t.co/vwhibg5nsM",
     "display_url": "pic.twitter.com/vwhibg5nsM",
     "expanded_url": "https://twitter.com/Wisdom_HQ/status/1620323784627724289/photo/1",
     "type": "photo",
     "sizes": {
      "medium": {
       "w": 960,
       "h": 1200,
       "resize": "fit"
      },
      "thumb": {
       "w": 150,
       "h": 150,
       "resize": "crop"
      },
      "large": {
       "w": 1620,
       "h": 2025,
       "resize": "fit"
      },
      "small": {
       "w": 544,
       "h": 680,
       "resize": "fit"
      }
     },
     "source_status_id": 1620323784627724289,
     "source_status_id_str": "1620323784627724289",
     "source_user_id": 1355814872408317958,
     "source_user_id_str": "1355814872408317958"
    }
   ]
  },
  "Fri Feb 17 06:53:55 +0000 2023": {
   "hashtags": [],
   "symbols": [],
   "user_mentions": [
    {
     "screen_name": "MKBHD",
     "name": "Marques Brownlee",
     "id": 29873662,
     "id_str": "29873662",
     "indices": [
      3,
      9
     ]
    },
    {
     "screen_name": "Erdayastronaut",
     "name": "Everyday Astronaut",
     "id": 3167257102,
     "id_str": "3167257102",
     "indices": [
      11,
      26
     ]
    }
   ],
   "urls": []
  },
  "Fri Feb 17 06:50:09 +0000 2023": {
   "hashtags": [],
   "symbols": [],
   "user_mentions": [
    {
     "screen_name": "MKBHD",
     "name": "Marques Brownlee",
     "id": 29873662,
     "id_str": "29873662",
     "indices": [
      3,
      9
     ]
    }
   ],
   "urls": []
  },
  "Fri Feb 17 06:49:25 +0000 2023": {
   "hashtags": [],
   "symbols": [],
   "user_mentions": [
    {
     "screen_name": "JaytunezBeatz",
     "name": "Big Jay \ud83e\udd85\ud83d\udc9c\u2764\ufe0f\ud83d\udcaf",
     "id": 961545605704282112,
     "id_str": "961545605704282112",
     "indices": [
      3,
      17
     ]
    },
    {
     "screen_name": "BinanceAfrica",
     "name": "Binance Africa",
     "id": 1051751414030987265,
     "id_str": "1051751414030987265",
     "indices": [
      19,
      33
     ]
    }
   ],
   "urls": []
  }
 }
}