{
 "969035588174163968": {
  "Mon Feb 20 15:12:58 +0000 2023": {
   "hashtags": [],
   "symbols": [],
   "user_mentions": [
    {
     "screen_name": "bennyjohnson",
     "name": "Benny Johnson",
     "id": 15212187,
     "id_str": "15212187",
     "indices": [
      3,
      16
     ]
    }
   ],
   "urls": []
  },
  "Mon Feb 20 15:12:21 +0000 2023": {
   "hashtags": [
    {
     "text": "China",
     "indices": [
      28,
      34
     ]
    },
    {
     "text": "America",
     "indices": [
      57,
      65
     ]
    },
    {
     "text": "Beijing",
     "indices": [
      76,
      84
     ]
    }
   ],
   "symbols": [],
   "user_mentions": [
    {
     "screen_name": "GordonGChang",
     "name": "Gordon G. Chang",
     "id": 151930383,
     "id_str": "151930383",
     "indices": [
      3,
      16
     ]
    }
   ],
   "urls": []
  },
  "Mon Feb 20 15:12:09 +0000 2023": {
   "hashtags": [],
   "symbols": [],
   "user_mentions": [
    {
     "screen_name": "RepMTG",
     "name": "Rep. Marjorie Taylor Greene\ud83c\uddfa\ud83c\uddf8",
     "id": 1344356576786866176,
     "id_str": "1344356576786866176",
     "indices": [
      3,
      10
     ]
    }
   ],
   "urls": []
  },
  "Mon Feb 20 15:12:01 +0000 2023": {
   "hashtags": [],
   "symbols": [],
   "user_mentions": [
    {
     "screen_name": "realjusthuman",
     "name": "Just Human",
     "id": 266354456,
     "id_str": "266354456",
     "indices": [
      3,
      17
     ]
    }
   ],
   "urls": []
  },
  "Mon Feb 20 15:11:53 +0000 2023": {
   "hashtags": [],
   "symbols": [],
   "user_mentions": [
    {
     "screen_name": "DonaldJTrumpJr",
     "name": "Donald Trump Jr.",
     "id": 39344374,
     "id_str": "39344374",
     "indices": [
      3,
      18
     ]
    }
   ],
   "urls": []
  },
  "Mon Feb 20 15:11:04 +0000 2023": {
   "hashtags": [],
   "symbols": [],
   "user_mentions": [],
   "urls": [],
   "media": [
    {
     "id": 1627687076853596161,
     "id_str": "1627687076853596161",
     "indices": [
      41,
      64
     ],
     "media_url": "http://pbs.twimg.com/media/Fpa0xcVaQAE5BTV.png",
     "media_url_https": "https://pbs.twimg.com/media/Fpa0xcVaQAE5BTV.png",
     "url": "https://t.co/faiLsWX74K",
     "display_url": "pic.twitter.com/faiLsWX74K",
     "expanded_url": "https://twitter.com/mymollycrow/status/1627687286740750336/photo/1",
     "type": "photo",
     "sizes": {
      "large": {
       "w": 681,
       "h": 403,
       "resize": "fit"
      },
      "medium": {
       "w": 681,
       "h": 403,
       "resize": "fit"
      },
      "small": {
       "w": 680,
       "h": 402,
       "resize": "fit"
      },
      "thumb": {
       "w": 150,
       "h": 150,
       "resize": "crop"
      }
     }
    }
   ]
  },
  "Mon Feb 20 15:09:29 +0000 2023": {
   "hashtags": [],
   "symbols": [],
   "user_mentions": [
    {
     "screen_name": "RichardGrenell",
     "name": "Richard Grenell",
     "id": 90480218,
     "id_str": "90480218",
     "indices": [
      3,
      18
     ]
    }
   ],
   "urls": []
  },
  "Mon Feb 20 14:46:31 +0000 2023": {
   "hashtags": [],
   "symbols": [],
   "user_mentions": [
    {
     "screen_name": "Pro__Trading",
     "name": "Pro Swing Trading \ud83d\udcc8\ud83d\ude0e\ud83c\uddfa\ud83c\uddf8",
     "id": 809455279825821696,
     "id_str": "809455279825821696",
     "indices": [
      3,
      16
     ]
    }
   ],
   "urls": []
  },
  "Mon Feb 20 14:40:16 +0000 2023": {
   "hashtags": [],
   "symbols": [],
   "user_mentions": [
    {
     "screen_name": "GailAlfarATX",
     "name": "Gail Alfar \ud83d\udc99",
     "id": 1233929232432205827,
     "id_str": "1233929232432205827",
     "indices": [
      3,
      16
     ]
    }
   ],
   "urls": []
  },
  "Mon Feb 20 14:34:50 +0000 2023": {
   "hashtags": [],
   "symbols": [],
   "user_mentions": [
    {
     "screen_name": "RepMTG",
     "name": "Rep. Marjorie Taylor Greene\ud83c\uddfa\ud83c\uddf8",
     "id": 1344356576786866176,
     "id_str": "1344356576786866176",
     "indices": [
      3,
      10
     ]
    }
   ],
   "urls": []
  },
  "Mon Feb 20 14:34:39 +0000 2023": {
   "hashtags": [],
   "symbols": [],
   "user_mentions": [
    {
     "screen_name": "mtgreenee",
     "name": "Marjorie Taylor Greene \ud83c\uddfa\ud83c\uddf8",
     "id": 826065164504006657,
     "id_str": "826065164504006657",
     "indices": [
      3,
      13
     ]
    }
   ],
   "urls": []
  },
  "Sun Feb 19 13:10:46 +0000 2023": {
   "hashtags": [],
   "symbols": [],
   "user_mentions": [
    {
     "screen_name": "mtaibbi",
     "name": "Matt Taibbi",
     "id": 38271276,
     "id_str": "38271276",
     "indices": [
      3,
      11
     ]
    }
   ],
   "urls": []
  },
  "Sun Feb 19 13:10:32 +0000 2023": {
   "hashtags": [],
   "symbols": [],
   "user_mentions": [
    {
     "screen_name": "colonelhomsi",
     "name": "Geo_monitor",
     "id": 1125633032,
     "id_str": "1125633032",
     "indices": [
      3,
      16
     ]
    }
   ],
   "urls": []
  },
  "Sun Feb 19 13:10:22 +0000 2023": {
   "hashtags": [],
   "symbols": [],
   "user_mentions": [
    {
     "screen_name": "ChoooCole",
     "name": "Chloe Cole \u2b50\ufe0f",
     "id": 1496333698706280454,
     "id_str": "1496333698706280454",
     "indices": [
      3,
      13
     ]
    },
    {
     "screen_name": "LexitMovement1",
     "name": "Lexit",
     "id": 1374217133211623427,
     "id_str": "1374217133211623427",
     "indices": [
      114,
      129
     ]
    }
   ],
   "urls": []
  },
  "Sun Feb 19 13:09:00 +0000 2023": {
   "hashtags": [],
   "symbols": [],
   "user_mentions": [
    {
     "screen_name": "Crimsontider",
     "name": "Debbie Dooley",
     "id": 21610240,
     "id_str": "21610240",
     "indices": [
      3,
      16
     ]
    }
   ],
   "urls": []
  },
  "Sun Feb 19 13:08:48 +0000 2023": {
   "hashtags": [],
   "symbols": [],
   "user_mentions": [
    {
     "screen_name": "WarMonitors",
     "name": "War Monitor",
     "id": 1392864463204782082,
     "id_str": "1392864463204782082",
     "indices": [
      3,
      15
     ]
    }
   ],
   "urls": [],
   "media": [
    {
     "id": 1627141367872000001,
     "id_str": "1627141367872000001",
     "indices": [
      22,
      45
     ],
     "media_url": "http://pbs.twimg.com/media/FpTEc_9akAELdXu.jpg",
     "media_url_https": "https://pbs.twimg.com/media/FpTEc_9akAELdXu.jpg",
     "url": "https://t.co/1Lv56sMhvT",
     "display_url": "pic.twitter.com/1Lv56sMhvT",
     "expanded_url": "https://twitter.com/WarMonitors/status/1627141372900777985/photo/1",
     "type": "photo",
     "sizes": {
      "thumb": {
       "w": 150,
       "h": 150,
       "resize": "crop"
      },
      "medium": {
       "w": 828,
       "h": 369,
       "resize": "fit"
      },
      "small": {
       "w": 680,
       "h": 303,
       "resize": "fit"
      },
      "large": {
       "w": 828,
       "h": 369,
       "resize": "fit"
      }
     },
     "source_status_id": 1627141372900777985,
     "source_status_id_str": "1627141372900777985",
     "source_user_id": 1392864463204782082,
     "source_user_id_str": "1392864463204782082"
    }
   ]
  },
  "Sun Feb 19 13:08:01 +0000 2023": {
   "hashtags": [],
   "symbols": [],
   "user_mentions": [
    {
     "screen_name": "PU28453638",
     "name": "Freedom \ud83c\uddfa\ud83c\uddf8\ud83e\udd85",
     "id": 1287788064450936834,
     "id_str": "1287788064450936834",
     "indices": [
      3,
      14
     ]
    }
   ],
   "urls": [],
   "media": [
    {
     "id": 1627168599524757504,
     "id_str": "1627168599524757504",
     "indices": [
      84,
      107
     ],
     "media_url": "http://pbs.twimg.com/media/FpTdOFxX0AAM9F1.jpg",
     "media_url_https": "https://pbs.twimg.com/media/FpTdOFxX0AAM9F1.jpg",
     "url": "https://t.co/0KqIsOkJkJ",
     "display_url": "pic.twitter.com/0KqIsOkJkJ",
     "expanded_url": "https://twitter.com/PU28453638/status/1627168963158282241/photo/1",
     "type": "photo",
     "sizes": {
      "thumb": {
       "w": 150,
       "h": 150,
       "resize": "crop"
      },
      "medium": {
       "w": 744,
       "h": 700,
       "resize": "fit"
      },
      "large": {
       "w": 744,
       "h": 700,
       "resize": "fit"
      },
      "small": {
       "w": 680,
       "h": 640,
       "resize": "fit"
      }
     },
     "source_status_id": 1627168963158282241,
     "source_status_id_str": "1627168963158282241",
     "source_user_id": 1287788064450936834,
     "source_user_id_str": "1287788064450936834"
    }
   ]
  },
  "Sun Feb 19 12:59:01 +0000 2023": {
   "hashtags": [
    {
     "text": "selfportrait",
     "indices": [
      23,
      36
     ]
    }
   ],
   "symbols": [],
   "user_mentions": [
    {
     "screen_name": "lsjourneys",
     "name": "Lsjourney",
     "id": 297764495,
     "id_str": "297764495",
     "indices": [
      3,
      14
     ]
    }
   ],
   "urls": [],
   "media": [
    {
     "id": 1625510681641472001,
     "id_str": "1625510681641472001",
     "indices": [
      113,
      136
     ],
     "media_url": "http://pbs.twimg.com/media/Fo75WkXX0AEJ5ut.jpg",
     "media_url_https": "https://pbs.twimg.com/media/Fo75WkXX0AEJ5ut.jpg",
     "url": "https://t.co/TaG4UK77LA",
     "display_url": "pic.twitter.com/TaG4UK77LA",
     "expanded_url": "https://twitter.com/lsjourneys/status/1625543722053124112/photo/1",
     "type": "photo",
     "sizes": {
      "small": {
       "w": 544,
       "h": 680,
       "resize": "fit"
      },
      "thumb": {
       "w": 150,
       "h": 150,
       "resize": "crop"
      },
      "medium": {
       "w": 960,
       "h": 1200,
       "resize": "fit"
      },
      "large": {
       "w": 1000,
       "h": 1250,
       "resize": "fit"
      }
     },
     "source_status_id": 1625543722053124112,
     "source_status_id_str": "1625543722053124112",
     "source_user_id": 297764495,
     "source_user_id_str": "297764495"
    }
   ]
  },
  "Sun Feb 19 12:57:09 +0000 2023": {
   "hashtags": [],
   "symbols": [],
   "user_mentions": [
    {
     "screen_name": "elonmusk",
     "name": "Elon Musk",
     "id": 44196397,
     "id_str": "44196397",
     "indices": [
      3,
      12
     ]
    },
    {
     "screen_name": "KanekoaTheGreat",
     "name": "kanekoa.substack.com",
     "id": 1085225533623783424,
     "id_str": "1085225533623783424",
     "indices": [
      14,
      30
     ]
    }
   ],
   "urls": []
  },
  "Sun Feb 19 12:11:56 +0000 2023": {
   "hashtags": [
    {
     "text": "Kiev",
     "indices": [
      107,
      112
     ]
    }
   ],
   "symbols": [],
   "user_mentions": [
    {
     "screen_name": "Ukraine66251776",
     "name": "UkraineNews",
     "id": 1517696955329228800,
     "id_str": "1517696955329228800",
     "indices": [
      3,
      19
     ]
    }
   ],
   "urls": []
  },
  "Sun Feb 19 12:09:26 +0000 2023": {
   "hashtags": [],
   "symbols": [],
   "user_mentions": [
    {
     "screen_name": "RepMTG",
     "name": "Rep. Marjorie Taylor Greene\ud83c\uddfa\ud83c\uddf8",
     "id": 1344356576786866176,
     "id_str": "1344356576786866176",
     "indices": [
      3,
      10
     ]
    }
   ],
   "urls": []
  },
  "Sun Feb 19 12:08:46 +0000 2023": {
   "hashtags": [],
   "symbols": [],
   "user_mentions": [
    {
     "screen_name": "StephenM",
     "name": "Stephen Miller",
     "id": 1329891389430243330,
     "id_str": "1329891389430243330",
     "indices": [
      3,
      12
     ]
    }
   ],
   "urls": []
  },
  "Sun Feb 19 12:08:40 +0000 2023": {
   "hashtags": [
    {
     "text": "Trump2024",
     "indices": [
      100,
      110
     ]
    }
   ],
   "symbols": [],
   "user_mentions": [
    {
     "screen_name": "ForgiatoBlow47",
     "name": "Trumps Nephew",
     "id": 1299776558354366465,
     "id_str": "1299776558354366465",
     "indices": [
      3,
      18
     ]
    }
   ],
   "urls": [],
   "media": [
    {
     "id": 1627092463356891138,
     "id_str": "1627092463356891138",
     "indices": [
      111,
      134
     ],
     "media_url": "http://pbs.twimg.com/media/FpSX-YcaUAINpWD.jpg",
     "media_url_https": "https://pbs.twimg.com/media/FpSX-YcaUAINpWD.jpg",
     "url": "https://t.co/XTNRn5FtQt",
     "display_url": "pic.twitter.com/XTNRn5FtQt",
     "expanded_url": "https://twitter.com/ForgiatoBlow47/status/1627092475100934146/photo/1",
     "type": "photo",
     "sizes": {
      "large": {
       "w": 680,
       "h": 656,
       "resize": "fit"
      },
      "thumb": {
       "w": 150,
       "h": 150,
       "resize": "crop"
      },
      "medium": {
       "w": 680,
       "h": 656,
       "resize": "fit"
      },
      "small": {
       "w": 680,
       "h": 656,
       "resize": "fit"
      }
     },
     "source_status_id": 1627092475100934146,
     "source_status_id_str": "1627092475100934146",
     "source_user_id": 1299776558354366465,
     "source_user_id_str": "1299776558354366465"
    }
   ]
  },
  "Sun Feb 19 12:08:32 +0000 2023": {
   "hashtags": [],
   "symbols": [],
   "user_mentions": [
    {
     "screen_name": "elonmusk",
     "name": "Elon Musk",
     "id": 44196397,
     "id_str": "44196397",
     "indices": [
      3,
      12
     ]
    }
   ],
   "urls": [],
   "media": [
    {
     "id": 1627055208844103680,
     "id_str": "1627055208844103680",
     "indices": [
      103,
      126
     ],
     "media_url": "http://pbs.twimg.com/media/FpR2F4kaEAAE9Xk.jpg",
     "media_url_https": "https://pbs.twimg.com/media/FpR2F4kaEAAE9Xk.jpg",
     "url": "https://t.co/4HgUSONvzw",
     "display_url": "pic.twitter.com/4HgUSONvzw",
     "expanded_url": "https://twitter.com/elonmusk/status/1627055215601147904/photo/1",
     "type": "photo",
     "sizes": {
      "large": {
       "w": 1284,
       "h": 906,
       "resize": "fit"
      },
      "thumb": {
       "w": 150,
       "h": 150,
       "resize": "crop"
      },
      "medium": {
       "w": 1200,
       "h": 847,
       "resize": "fit"
      },
      "small": {
       "w": 680,
       "h": 480,
       "resize": "fit"
      }
     },
     "source_status_id": 1627055215601147904,
     "source_status_id_str": "1627055215601147904",
     "source_user_id": 44196397,
     "source_user_id_str": "44196397"
    }
   ]
  },
  "Sun Feb 19 12:08:25 +0000 2023": {
   "hashtags": [],
   "symbols": [],
   "user_mentions": [
    {
     "screen_name": "realLizUSA",
     "name": "Liz Harrington",
     "id": 757832485,
     "id_str": "757832485",
     "indices": [
      3,
      14
     ]
    }
   ],
   "urls": []
  },
  "Sun Feb 19 12:08:09 +0000 2023": {
   "hashtags": [],
   "symbols": [],
   "user_mentions": [
    {
     "screen_name": "realLizUSA",
     "name": "Liz Harrington",
     "id": 757832485,
     "id_str": "757832485",
     "indices": [
      3,
      14
     ]
    }
   ],
   "urls": []
  },
  "Sun Feb 19 12:07:57 +0000 2023": {
   "hashtags": [],
   "symbols": [],
   "user_mentions": [
    {
     "screen_name": "elonmusk",
     "name": "Elon Musk",
     "id": 44196397,
     "id_str": "44196397",
     "indices": [
      3,
      12
     ]
    }
   ],
   "urls": [],
   "media": [
    {
     "id": 1627246530309627904,
     "id_str": "1627246530309627904",
     "indices": [
      14,
      37
     ],
     "media_url": "http://pbs.twimg.com/media/FpUkGQkXoAAwzwE.jpg",
     "media_url_https": "https://pbs.twimg.com/media/FpUkGQkXoAAwzwE.jpg",
     "url": "https://t.co/O3nGpfeRZ7",
     "display_url": "pic.twitter.com/O3nGpfeRZ7",
     "expanded_url": "https://twitter.com/elonmusk/status/1627246535581761536/photo/1",
     "type": "photo",
     "sizes": {
      "thumb": {
       "w": 150,
       "h": 150,
       "resize": "crop"
      },
      "medium": {
       "w": 460,
       "h": 647,
       "resize": "fit"
      },
      "small": {
       "w": 460,
       "h": 647,
       "resize": "fit"
      },
      "large": {
       "w": 460,
       "h": 647,
       "resize": "fit"
      }
     },
     "source_status_id": 1627246535581761536,
     "source_status_id_str": "1627246535581761536",
     "source_user_id": 44196397,
     "source_user_id_str": "44196397"
    }
   ]
  },
  "Sun Feb 19 12:07:29 +0000 2023": {
   "hashtags": [],
   "symbols": [],
   "user_mentions": [
    {
     "screen_name": "elonmusk",
     "name": "Elon Musk",
     "id": 44196397,
     "id_str": "44196397",
     "indices": [
      3,
      12
     ]
    }
   ],
   "urls": [],
   "media": [
    {
     "id": 1626703662197387264,
     "id_str": "1626703662197387264",
     "indices": [
      95,
      118
     ],
     "media_url": "http://pbs.twimg.com/media/FpM2XLQaMAAsnhY.jpg",
     "media_url_https": "https://pbs.twimg.com/media/FpM2XLQaMAAsnhY.jpg",
     "url": "https://t.co/vbeOOqKuyT",
     "display_url": "pic.twitter.com/vbeOOqKuyT",
     "expanded_url": "https://twitter.com/elonmusk/status/1626703667591270400/photo/1",
     "type": "photo",
     "sizes": {
      "thumb": {
       "w": 150,
       "h": 150,
       "resize": "crop"
      },
      "medium": {
       "w": 1159,
       "h": 845,
       "resize": "fit"
      },
      "large": {
       "w": 1159,
       "h": 845,
       "resize": "fit"
      },
      "small": {
       "w": 680,
       "h": 496,
       "resize": "fit"
      }
     },
     "source_status_id": 1626703667591270400,
     "source_status_id_str": "1626703667591270400",
     "source_user_id": 44196397,
     "source_user_id_str": "44196397"
    }
   ]
  },
  "Sun Feb 19 12:07:25 +0000 2023": {
   "hashtags": [],
   "symbols": [],
   "user_mentions": [
    {
     "screen_name": "elonmusk",
     "name": "Elon Musk",
     "id": 44196397,
     "id_str": "44196397",
     "indices": [
      3,
      12
     ]
    }
   ],
   "urls": []
  },
  "Sat Feb 18 04:54:25 +0000 2023": {
   "hashtags": [],
   "symbols": [],
   "user_mentions": [
    {
     "screen_name": "theRealKiyosaki",
     "name": "Robert Kiyosaki",
     "id": 29856819,
     "id_str": "29856819",
     "indices": [
      3,
      19
     ]
    }
   ],
   "urls": []
  },
  "Sat Feb 18 04:25:41 +0000 2023": {
   "hashtags": [],
   "symbols": [],
   "user_mentions": [
    {
     "screen_name": "Solmemes1",
     "name": "Sol\ud83c\udfac",
     "id": 997503485707943937,
     "id_str": "997503485707943937",
     "indices": [
      3,
      13
     ]
    }
   ],
   "urls": []
  },
  "Sat Feb 18 03:54:28 +0000 2023": {
   "hashtags": [],
   "symbols": [],
   "user_mentions": [
    {
     "screen_name": "RichardGrenell",
     "name": "Richard Grenell",
     "id": 90480218,
     "id_str": "90480218",
     "indices": [
      3,
      18
     ]
    }
   ],
   "urls": []
  },
  "Sat Feb 18 03:49:54 +0000 2023": {
   "hashtags": [
    {
     "text": "Trump2024",
     "indices": [
      58,
      68
     ]
    }
   ],
   "symbols": [],
   "user_mentions": [
    {
     "screen_name": "kimguilfoyle",
     "name": "Kimberly Guilfoyle",
     "id": 25101996,
     "id_str": "25101996",
     "indices": [
      3,
      16
     ]
    }
   ],
   "urls": [],
   "media": [
    {
     "id": 1626643416980365314,
     "id_str": "1626643416980365314",
     "indices": [
      69,
      92
     ],
     "media_url": "http://pbs.twimg.com/media/FpL_kcVXoAIUdPz.jpg",
     "media_url_https": "https://pbs.twimg.com/media/FpL_kcVXoAIUdPz.jpg",
     "url": "https://t.co/9YySdABvFY",
     "display_url": "pic.twitter.com/9YySdABvFY",
     "expanded_url": "https://twitter.com/kimguilfoyle/status/1626643425125666833/photo/1",
     "type": "photo",
     "sizes": {
      "thumb": {
       "w": 150,
       "h": 150,
       "resize": "crop"
      },
      "small": {
       "w": 480,
       "h": 640,
       "resize": "fit"
      },
      "large": {
       "w": 480,
       "h": 640,
       "resize": "fit"
      },
      "medium": {
       "w": 480,
       "h": 640,
       "resize": "fit"
      }
     },
     "source_status_id": 1626643425125666833,
     "source_status_id_str": "1626643425125666833",
     "source_user_id": 25101996,
     "source_user_id_str": "25101996"
    }
   ]
  },
  "Fri Feb 17 12:57:20 +0000 2023": {
   "hashtags": [],
   "symbols": [],
   "user_mentions": [
    {
     "screen_name": "realLizUSA",
     "name": "Liz Harrington",
     "id": 757832485,
     "id_str": "757832485",
     "indices": [
      3,
      14
     ]
    }
   ],
   "urls": []
  },
  "Fri Feb 17 12:54:18 +0000 2023": {
   "hashtags": [],
   "symbols": [],
   "user_mentions": [
    {
     "screen_name": "RealMattCouch",
     "name": "Matt Couch",
     "id": 601535938,
     "id_str": "601535938",
     "indices": [
      3,
      17
     ]
    }
   ],
   "urls": []
  },
  "Fri Feb 17 12:50:33 +0000 2023": {
   "hashtags": [],
   "symbols": [],
   "user_mentions": [
    {
     "screen_name": "elonmusk",
     "name": "Elon Musk",
     "id": 44196397,
     "id_str": "44196397",
     "indices": [
      3,
      12
     ]
    }
   ],
   "urls": []
  }
 }
}